{
  "0": {
    "COMENNT": "Ha davvero bisogno di vincere presto un torneo. Dobbiamo fare qualcosa...",
    "MAX_HP": "",
    "POWER": "",
    "SPEED": "",
    "TECHNIQUE": "",
    "SHAPE": "",
    "BELIVE": "",
    "HACT_NUM": "",
    "SKILL_NUM": "",
    "TURN_NUM": "40"
  },
  "1": {
    "COMENNT": "Tokita non ti ascolterà mai a meno che tu non sviluppi prima la Fiducia con lui. Che ne dici di portarlo a bere qualcosa?",
    "MAX_HP": "",
    "POWER": "",
    "SPEED": "",
    "TECHNIQUE": "",
    "SHAPE": "",
    "BELIVE": "★20",
    "HACT_NUM": "",
    "SKILL_NUM": "",
    "TURN_NUM": ""
  },
  "2": {
    "COMENNT": "Onestamente, non ha bisogno di altro allenamento. Non dovrebbe avere problemi a combattere in un torneo.",
    "MAX_HP": "700",
    "POWER": "60",
    "SPEED": "80",
    "TECHNIQUE": "90",
    "SHAPE": "",
    "BELIVE": "",
    "HACT_NUM": "",
    "SKILL_NUM": "",
    "TURN_NUM": ""
  },
  "3": {
    "COMENNT": "La sua Tecnica non migliorerà ulteriormente. Ha già molte abilità. Perché non lo fai competere in un incontro vero?",
    "MAX_HP": "",
    "POWER": "",
    "SPEED": "",
    "TECHNIQUE": "90",
    "SHAPE": "",
    "BELIVE": "",
    "HACT_NUM": "",
    "SKILL_NUM": "",
    "TURN_NUM": ""
  },
  "4": {
    "COMENNT": "La sua Velocità non migliorerà ulteriormente. Ha già molte abilità. Perché non lo fai competere in un incontro vero?",
    "MAX_HP": "",
    "POWER": "",
    "SPEED": "80",
    "TECHNIQUE": "",
    "SHAPE": "",
    "BELIVE": "",
    "HACT_NUM": "",
    "SKILL_NUM": "",
    "TURN_NUM": ""
  },
  "5": {
    "COMENNT": "La sua Potenza non migliorerà ulteriormente. Ha già molte abilità. Perché non lo fai competere in un incontro vero?",
    "MAX_HP": "",
    "POWER": "60",
    "SPEED": "",
    "TECHNIQUE": "",
    "SHAPE": "",
    "BELIVE": "",
    "HACT_NUM": "",
    "SKILL_NUM": "",
    "TURN_NUM": ""
  },
  "6": {
    "COMENNT": "È diventato un combattente esemplare. Sono sicuro che può cavarsela in un torneo! Proviamoci!",
    "MAX_HP": "650",
    "POWER": "50",
    "SPEED": "65",
    "TECHNIQUE": "75",
    "SHAPE": "",
    "BELIVE": "",
    "HACT_NUM": "",
    "SKILL_NUM": "",
    "TURN_NUM": ""
  },
  "7": {
    "COMENNT": "La sua Tecnica è superba! Se lavori per rafforzare i suoi punti deboli, sono sicuro che vincerà un torneo.",
    "MAX_HP": "",
    "POWER": "",
    "SPEED": "",
    "TECHNIQUE": "75",
    "SHAPE": "",
    "BELIVE": "",
    "HACT_NUM": "",
    "SKILL_NUM": "",
    "TURN_NUM": ""
  },
  "8": {
    "COMENNT": "La sua Velocità è superba! Se lavori per rafforzare i suoi punti deboli, sono sicuro che vincerà un torneo.",
    "MAX_HP": "",
    "POWER": "",
    "SPEED": "65",
    "TECHNIQUE": "",
    "SHAPE": "",
    "BELIVE": "",
    "HACT_NUM": "",
    "SKILL_NUM": "",
    "TURN_NUM": ""
  },
  "9": {
    "COMENNT": "La sua Potenza è superba! Se lavori per rafforzare i suoi punti deboli, sono sicuro che vincerà un torneo.",
    "MAX_HP": "",
    "POWER": "50",
    "SPEED": "",
    "TECHNIQUE": "",
    "SHAPE": "",
    "BELIVE": "",
    "HACT_NUM": "",
    "SKILL_NUM": "",
    "TURN_NUM": ""
  },
  "10": {
    "COMENNT": "È diventato un combattente spettacolare. Potrebbe essere pronto per un incontro di esibizione di medio livello.",
    "MAX_HP": "650",
    "POWER": "40",
    "SPEED": "50",
    "TECHNIQUE": "55",
    "SHAPE": "",
    "BELIVE": "",
    "HACT_NUM": "",
    "SKILL_NUM": "",
    "TURN_NUM": ""
  },
  "11": {
    "COMENNT": "Ha un'ottima Stamina. Continua così e lavora anche sulle sue altre abilità. Sono sicuro che la sua Tecnica si svilupperà ulteriormente.",
    "MAX_HP": "650",
    "POWER": "",
    "SPEED": "",
    "TECHNIQUE": "",
    "SHAPE": "",
    "BELIVE": "",
    "HACT_NUM": "",
    "SKILL_NUM": "",
    "TURN_NUM": ""
  },
  "12": {
    "COMENNT": "La sua Tecnica è migliorata molto. Questa è la sua specialità, quindi continua a lavorarci anche in futuro.",
    "MAX_HP": "",
    "POWER": "",
    "SPEED": "",
    "TECHNIQUE": "55",
    "SHAPE": "",
    "BELIVE": "",
    "HACT_NUM": "",
    "SKILL_NUM": "",
    "TURN_NUM": ""
  },
  "13": {
    "COMENNT": "È diventato molto più veloce. Scommetto che può diventare ancora più veloce, quindi continuiamo a lavorare sulla sua Velocità.",
    "MAX_HP": "",
    "POWER": "",
    "SPEED": "50",
    "TECHNIQUE": "",
    "SHAPE": "",
    "BELIVE": "",
    "HACT_NUM": "",
    "SKILL_NUM": "",
    "TURN_NUM": ""
  },
  "14": {
    "COMENNT": "La sua Potenza si sta sviluppando bene. Rispetto ad altre abilità, la sua Potenza si sviluppa lentamente, ma non c'è da preoccuparsi!",
    "MAX_HP": "",
    "POWER": "40",
    "SPEED": "",
    "TECHNIQUE": "",
    "SHAPE": "",
    "BELIVE": "",
    "HACT_NUM": "",
    "SKILL_NUM": "",
    "TURN_NUM": ""
  },
  "15": {
    "COMENNT": "Sta crescendo a un ritmo ben bilanciato. La sua Tecnica è particolarmente promettente. Facciamolo competere in molte partite!",
    "MAX_HP": "550",
    "POWER": "30",
    "SPEED": "35",
    "TECHNIQUE": "40",
    "SHAPE": "",
    "BELIVE": "",
    "HACT_NUM": "",
    "SKILL_NUM": "",
    "TURN_NUM": ""
  },
  "16": {
    "COMENNT": "Ha esperienza, quindi ha imparato le basi. Ma può essere difficile da gestire, quindi cerca di guadagnare la sua Fiducia e osserva il suo Umore.",
    "MAX_HP": "",
    "POWER": "",
    "SPEED": "",
    "TECHNIQUE": "",
    "SHAPE": "",
    "BELIVE": "",
    "HACT_NUM": "",
    "SKILL_NUM": "",
    "TURN_NUM": ""
  },
  "types": {
    "COMENNT": "string",
    "MAX_HP": "string",
    "POWER": "string",
    "SPEED": "string",
    "TECHNIQUE": "string",
    "SHAPE": "string",
    "BELIVE": "string",
    "HACT_NUM": "string",
    "SKILL_NUM": "string",
    "TURN_NUM": "string"
  }
}